.gitignore
.travis.yml
CHANGES.txt
CONTRIBUTORS.txt
LICENSE
MANIFEST.in
README.rst
README.txt
bootstrap.py
buildout.cfg
setup.py
docs/INSTALL.txt
docs/LICENSE.GPL
docs/LICENSE.txt
fourdigits/__init__.py
fourdigits.portlet.keywordrelated.egg-info/PKG-INFO
fourdigits.portlet.keywordrelated.egg-info/SOURCES.txt
fourdigits.portlet.keywordrelated.egg-info/dependency_links.txt
fourdigits.portlet.keywordrelated.egg-info/entry_points.txt
fourdigits.portlet.keywordrelated.egg-info/namespace_packages.txt
fourdigits.portlet.keywordrelated.egg-info/not-zip-safe
fourdigits.portlet.keywordrelated.egg-info/requires.txt
fourdigits.portlet.keywordrelated.egg-info/top_level.txt
fourdigits/portlet/__init__.py
fourdigits/portlet/keywordrelated/__init__.py
fourdigits/portlet/keywordrelated/configure.zcml
fourdigits/portlet/keywordrelated/keywordrelatedportlet.pt
fourdigits/portlet/keywordrelated/keywordrelatedportlet.py
fourdigits/portlet/keywordrelated/profiles/default/metadata.xml
fourdigits/portlet/keywordrelated/profiles/default/portlets.xml
fourdigits/portlet/keywordrelated/tests/__init__.py
fourdigits/portlet/keywordrelated/tests/base.py
fourdigits/portlet/keywordrelated/tests/test_portlet.py