Metadata-Version: 1.0
Name: fourdigits.portlet.keywordrelated
Version: 0.3
Summary: A portlet showing related items, based on the current contexts tags.
Home-page: https://github.com/collective/fourdigits.portlet.keywordrelated
Author: Four Digits
Author-email: info@fourdigits.nl
License: gpl
Platform: UNKNOWN
Classifier: Framework :: Plone
Classifier: Programming Language :: Python
